super_resolution_gans/__init__.py
super_resolution_gans/srgan_utils.py
SuperResolution_GANs-0.0.5.dist-info/LICENSE.txt
SuperResolution_GANs-0.0.5.dist-info/METADATA
SuperResolution_GANs-0.0.5.dist-info/WHEEL
SuperResolution_GANs-0.0.5.dist-info/top_level.txt
SuperResolution_GANs-0.0.5.dist-info/RECORD
