Metadata-Version: 2.1
Name: SuperResolution-GANs
Version: 0.0.5
Summary: Super Resolution Image
Home-page: https://github.com/AbdullahAbdelhakeem6484/ITI_Graduation_Project1_SISR_BY_GAN
Author: Abdullah Abdelhakeem
Author-email: abdullah.abdelhakeem25@gmail.com
License: UNKNOWN
Platform: UNKNOWN
Classifier: Programming Language :: Python :: 3
Classifier: License :: OSI Approved :: MIT License
Classifier: Operating System :: OS Independent
Requires-Python: >=3.7
License-File: LICENSE.txt
